Metadata-Version: 1.0
Name: annoyclients
Version: 0.0.1
Summary: Annoy Client
Home-page: UNKNOWN
Author: USopaoglu
Author-email: UNKNOWN
License: UNKNOWN
Platform: UNKNOWN
